streamlit_force_graph_simulator/__init__.py
streamlit_force_graph_simulator/forcegraphsimulation.py
streamlit_force_graph_simulator/frontend/build/asset-manifest.json
streamlit_force_graph_simulator/frontend/build/bootstrap.min.css
streamlit_force_graph_simulator/frontend/build/index.html
streamlit_force_graph_simulator/frontend/build/precache-manifest.1bd7eb049e380617636eb2a20a5235e9.js
streamlit_force_graph_simulator/frontend/build/precache-manifest.ceb2cec2e65cca867694c48f98f5be95.js
streamlit_force_graph_simulator/frontend/build/service-worker.js
streamlit_force_graph_simulator/frontend/build/static/js/2.23f7626a.chunk.js
streamlit_force_graph_simulator/frontend/build/static/js/2.23f7626a.chunk.js.LICENSE.txt
streamlit_force_graph_simulator/frontend/build/static/js/2.23f7626a.chunk.js.map
streamlit_force_graph_simulator/frontend/build/static/js/2.ddfd28cd.chunk.js
streamlit_force_graph_simulator/frontend/build/static/js/2.ddfd28cd.chunk.js.LICENSE.txt
streamlit_force_graph_simulator/frontend/build/static/js/2.ddfd28cd.chunk.js.map
streamlit_force_graph_simulator/frontend/build/static/js/main.3cc30e2c.chunk.js
streamlit_force_graph_simulator/frontend/build/static/js/main.3cc30e2c.chunk.js.map
streamlit_force_graph_simulator/frontend/build/static/js/main.a0c30abb.chunk.js
streamlit_force_graph_simulator/frontend/build/static/js/main.a0c30abb.chunk.js.map
streamlit_force_graph_simulator/frontend/build/static/js/runtime-main.3ca778a4.js
streamlit_force_graph_simulator/frontend/build/static/js/runtime-main.3ca778a4.js.map
streamlit_force_graph_simulator/frontend/build/static/media/bezier.9cfe50b6.cjs
streamlit_force_graph_simulator-0.0.2.dist-info/METADATA
streamlit_force_graph_simulator-0.0.2.dist-info/WHEEL
streamlit_force_graph_simulator-0.0.2.dist-info/top_level.txt
streamlit_force_graph_simulator-0.0.2.dist-info/RECORD
