Metadata-Version: 2.1
Name: streamlit-force-graph-simulator
Version: 0.0.2
Summary: Linking python with visualizing processes on and off networks.
Home-page: UNKNOWN
Author: Erik Weis
Author-email: erik.weis@uvm.edu
License: UNKNOWN
Platform: UNKNOWN
Requires-Python: >=3.6
Requires-Dist: streamlit (>=0.63)
